cybergenetics/__init__.py
cybergenetics/__main__.py
cybergenetics/cli.py
cybergenetics/control/__init__.py
cybergenetics/control/control.py
cybergenetics/control/wrappers.py
cybergenetics/envs/__init__.py
cybergenetics/envs/assets/crn/ecoli.py
cybergenetics/envs/assets/crn/yeast.py
cybergenetics/envs/coculture.py
cybergenetics/envs/crn.py
cybergenetics/wrappers/__init__.py
cybergenetics/wrappers/as_tensor.py
cybergenetics-0.1.0.dist-info/entry_points.txt
cybergenetics-0.1.0.dist-info/LICENSE
cybergenetics-0.1.0.dist-info/WHEEL
cybergenetics-0.1.0.dist-info/METADATA
cybergenetics-0.1.0.dist-info/RECORD
