Metadata-Version: 2.1
Name: cybergenetics
Version: 0.1.0
Summary: Cybergenetics is a controlled simulating environment for chemical reaction networks (CRNs) and co-cultures.
Home-page: https://cybergenetics.readthedocs.io/en/latest/
License: BSD-3-Clause
Author: Yi Zhang, Quentin Badolle
Requires-Python: >=3.7,<4.0
Classifier: License :: OSI Approved :: BSD License
Classifier: Programming Language :: Python :: 3
Classifier: Programming Language :: Python :: 3.10
Classifier: Programming Language :: Python :: 3.7
Classifier: Programming Language :: Python :: 3.8
Classifier: Programming Language :: Python :: 3.9
Requires-Dist: gym (>=0.23.1,<0.24.0)
Requires-Dist: imageio (>=2.20.0,<3.0.0)
Requires-Dist: sdeint (>=0.3.0,<0.4.0)
Requires-Dist: seaborn (>=0.11.2,<0.12.0)
Requires-Dist: torch (>=1.12.0,<2.0.0)
Project-URL: Documentation, https://cybergenetics.readthedocs.io/en/latest/
Project-URL: Repository, https://github.com/imyizhang/cybergenetics
